mcp_google_sheets/__init__.py
mcp_google_sheets/server.py
temy_google_workspace_mcp-0.1.1.dist-info/METADATA
temy_google_workspace_mcp-0.1.1.dist-info/WHEEL
temy_google_workspace_mcp-0.1.1.dist-info/entry_points.txt
temy_google_workspace_mcp-0.1.1.dist-info/licenses/LICENSE
temy_google_workspace_mcp-0.1.1.dist-info/RECORD
