Metadata-Version: 2.4
Name: temy-google-workspace-mcp
Version: 0.1.1
Summary: MCP server for Google Workspace - read/write Google Sheets and Google Docs.
Project-URL: Homepage, https://github.com/yardobr/mcp-google-sheets
Project-URL: Bug Tracker, https://github.com/yardobr/mcp-google-sheets/issues
Project-URL: Repository, https://github.com/yardobr/mcp-google-sheets.git
Author-email: Yaroslav Dobroskok <yar.dobroskok@gmail.com>
License-File: LICENSE
Requires-Python: >=3.10
Requires-Dist: google-api-python-client>=2.117.0
Requires-Dist: google-auth-oauthlib>=1.2.0
Requires-Dist: google-auth>=2.28.1
Requires-Dist: mcp>=1.5.0
